nmea2000/__init__.py
nmea2000/cli.py
nmea2000/consts.py
nmea2000/decoder.py
nmea2000/encoder.py
nmea2000/ioclient.py
nmea2000/message.py
nmea2000/pgns.py
nmea2000/utils.py
nmea2000-2025.10.13.dist-info/licenses/LICENSE
tests/NMEA2000TestServer.py
tests/__init__.py
tests/conftest.py
tests/test_decoder.py
tests/test_encoder.py
tests/test_recombine.py
tests/test_tcp_client.py
tests/test_utils.py
nmea2000-2025.10.13.dist-info/METADATA
nmea2000-2025.10.13.dist-info/WHEEL
nmea2000-2025.10.13.dist-info/entry_points.txt
nmea2000-2025.10.13.dist-info/top_level.txt
nmea2000-2025.10.13.dist-info/RECORD
