Metadata-Version: 2.4
Name: nmea2000
Version: 2025.10.13
Summary: NMEA 2000 encoder and decoder
Home-page: https://github.com/tomer-w/nmea2000
Author: Tomer-W
License: Apache-2.0
License-File: LICENSE
Requires-Dist: orjson<4.0,>=3.10
Requires-Dist: pyserial-asyncio>=0.6
Requires-Dist: tenacity>=9.0.0
Dynamic: author
Dynamic: description
Dynamic: description-content-type
Dynamic: home-page
Dynamic: license
Dynamic: license-file
Dynamic: requires-dist
Dynamic: summary
